pymodaq_plugins_physik_instrumente/__init__.py
pymodaq_plugins_physik_instrumente/utils.py
pymodaq_plugins_physik_instrumente/daq_move_plugins/__init__.py
pymodaq_plugins_physik_instrumente/daq_move_plugins/daq_move_PI.py
pymodaq_plugins_physik_instrumente/daq_move_plugins/daq_move_PILegacy.py
pymodaq_plugins_physik_instrumente/daq_move_plugins/daq_move_PI_E870.py
pymodaq_plugins_physik_instrumente/daq_move_plugins/daq_move_PI_MMC.py
pymodaq_plugins_physik_instrumente/daq_move_plugins/daq_move_PI_MMCLegacy.py
pymodaq_plugins_physik_instrumente/daq_viewer_plugins/__init__.py
pymodaq_plugins_physik_instrumente/daq_viewer_plugins/plugins_0D/__init__.py
pymodaq_plugins_physik_instrumente/daq_viewer_plugins/plugins_1D/__init__.py
pymodaq_plugins_physik_instrumente/daq_viewer_plugins/plugins_2D/__init__.py
pymodaq_plugins_physik_instrumente/daq_viewer_plugins/plugins_ND/__init__.py
pymodaq_plugins_physik_instrumente/hardware/__init__.py
pymodaq_plugins_physik_instrumente/hardware/pi_wrapper.py
pymodaq_plugins_physik_instrumente/hardware/PI/MMC.H
pymodaq_plugins_physik_instrumente/hardware/PI/MMC.dll
pymodaq_plugins_physik_instrumente/hardware/PI/MMC413.H
pymodaq_plugins_physik_instrumente/hardware/PI/MMC413.c
pymodaq_plugins_physik_instrumente/hardware/PI/MMC413.lib
pymodaq_plugins_physik_instrumente/hardware/PI/MMC_418.dll
pymodaq_plugins_physik_instrumente/hardware/PI/MercuryNativeCommands_MS176E101.pdf
pymodaq_plugins_physik_instrumente/hardware/PI/Mercury_DLL-LV_MS177E500.pdf
pymodaq_plugins_physik_instrumente/hardware/PI/__init__.py
pymodaq_plugins_physik_instrumente/hardware/PI/base.py
pymodaq_plugins_physik_instrumente/hardware/PI/mmc_wrapper.py
pymodaq_plugins_physik_instrumente/hardware/PI/mmc_wrapper_client64.py
pymodaq_plugins_physik_instrumente/resources/__init__.py
pymodaq_plugins_physik_instrumente/resources/config_template.toml
pymodaq_plugins_physik_instrumente-2.0.3.dist-info/METADATA
pymodaq_plugins_physik_instrumente-2.0.3.dist-info/WHEEL
pymodaq_plugins_physik_instrumente-2.0.3.dist-info/entry_points.txt
pymodaq_plugins_physik_instrumente-2.0.3.dist-info/licenses/LICENSE
pymodaq_plugins_physik_instrumente-2.0.3.dist-info/RECORD
