Metadata-Version: 2.4
Name: pymodaq_plugins_physik_instrumente
Version: 2.0.3
Summary: Set of PyMoDAQ plugins for Actuators from Physik Instumente (All the ones compatible with the GCS2 commands as well as the old 32bits MMC controller...)
Project-URL: Homepage, https://pymodaq.cnrs.fr
Project-URL: Documentation , https://pymodaq.cnrs.fr
Project-URL: Repository , https://github.com/PyMoDAQ/pymodaq_plugins_physik_instrumente
Author-email: "Sebastien J. Weber" <sebastien.weber@cemes.fr>
Maintainer-email: "Sebastien J. Weber" <sebastien.weber@cemes.fr>
License: The MIT License (MIT)
License-File: LICENSE
Classifier: Development Status :: 5 - Production/Stable
Classifier: Intended Audience :: Science/Research
Classifier: License :: OSI Approved :: MIT License
Classifier: Natural Language :: English
Classifier: Operating System :: OS Independent
Classifier: Programming Language :: Python :: 3.8
Classifier: Programming Language :: Python :: 3.9
Classifier: Programming Language :: Python :: 3.10
Classifier: Programming Language :: Python :: 3.11
Classifier: Topic :: Scientific/Engineering :: Human Machine Interfaces
Classifier: Topic :: Scientific/Engineering :: Visualization
Classifier: Topic :: Software Development :: Libraries :: Python Modules
Classifier: Topic :: Software Development :: User Interfaces
Requires-Python: >=3.8
Requires-Dist: bitstring
Requires-Dist: msl-loadlib
Requires-Dist: pipython
Requires-Dist: pymodaq>=5.0.0
